{"nodes": [{"id": "public_platforms_codechef", "label": "CodeChef Logo", "file_type": "image", "source_file": "/Users/ankitnagar/desktop/Geeky Frontend new /public/platforms/codechef.svg", "source_location": null, "source_url": null, "captured_at": null, "author": null, "contributor": null}, {"id": "platform_codechef", "label": "CodeChef (Platform)", "file_type": "concept", "source_file": "/Users/ankitnagar/desktop/Geeky Frontend new /public/platforms/codechef.svg", "source_location": null, "source_url": null, "captured_at": null, "author": null, "contributor": null}], "edges": [], "hyperedges": []}